<?xml version="1.0" encoding="utf-8" ?>
<dwsync>
<file name="cake.icon.png" server="ftp.tailoredpages.com//iCueCards/" local="129669582580000000" remote="129688517400000000" />
<file name="cake.power.gif" server="ftp.tailoredpages.com//iCueCards/" local="129669582580000000" remote="129688517400000000" />
<file name="test-error-icon.png" server="ftp.tailoredpages.com//iCueCards/" local="129669582580000000" remote="129688517400000000" />
<file name="test-fail-icon.png" server="ftp.tailoredpages.com//iCueCards/" local="129669582580000000" remote="129688518000000000" />
<file name="test-pass-icon.png" server="ftp.tailoredpages.com//iCueCards/" local="129669582580000000" remote="129688518000000000" />
<file name="test-skip-icon.png" server="ftp.tailoredpages.com//iCueCards/" local="129669582580000000" remote="129688518000000000" />
<file name="cake.icon.png" server="ftp.tailoredpages.com//weavapp/" local="129669582580000000" remote="130165334400000000" />
<file name="cake.power.gif" server="ftp.tailoredpages.com//weavapp/" local="129669582580000000" remote="130165334400000000" />
<file name="test-error-icon.png" server="ftp.tailoredpages.com//weavapp/" local="129669582580000000" remote="130165334400000000" />
<file name="test-fail-icon.png" server="ftp.tailoredpages.com//weavapp/" local="129669582580000000" remote="130165334400000000" />
<file name="test-pass-icon.png" server="ftp.tailoredpages.com//weavapp/" local="129669582580000000" remote="130165334400000000" />
<file name="test-skip-icon.png" server="ftp.tailoredpages.com//weavapp/" local="129669582580000000" remote="130165334400000000" />
<file name="Aeroplane.png" server="ftp.tailoredpages.com//weavapp/" local="130110421300000000" remote="130165355400000000" />
<file name="Anytime.png" server="ftp.tailoredpages.com//weavapp/" local="130146839561585103" remote="130165355400000000" />
<file name="carousel.jpeg" server="ftp.tailoredpages.com//weavapp/" local="130110409460000000" remote="130165355400000000" />
<file name="company_logo-bcg.jpg" server="ftp.tailoredpages.com//weavapp/" local="130142628847254416" remote="130165356000000000" />
<file name="company_logo-ernst.jpg" server="ftp.tailoredpages.com//weavapp/" local="130142629118979957" remote="130165356000000000" />
<file name="company_logo-goldman.gif" server="ftp.tailoredpages.com//weavapp/" local="130142628315203984" remote="130165356000000000" />
<file name="company_logo-proctor.jpg" server="ftp.tailoredpages.com//weavapp/" local="130142628535926609" remote="130165356000000000" />
<file name="cross1.png" server="ftp.tailoredpages.com//weavapp/" local="130136639063205793" remote="130165356000000000" />
<file name="glyphicons-halflings-white.png" server="ftp.tailoredpages.com//weavapp/" local="130097547300000000" remote="130165356000000000" />
<file name="glyphicons-halflings.png" server="ftp.tailoredpages.com//weavapp/" local="130097547300000000" remote="130165356000000000" />
<file name="huge-phone.png" server="ftp.tailoredpages.com//weavapp/" local="130110439240000000" remote="130165356000000000" />
<file name="iphone-placeholder.png" server="ftp.tailoredpages.com//weavapp/" local="130110437540000000" remote="130165356000000000" />
<file name="logoplaceholder.png" server="ftp.tailoredpages.com//weavapp/" local="130097545380000000" remote="130165356000000000" />
<file name="Match.png" server="ftp.tailoredpages.com//weavapp/" local="130146839708653515" remote="130165356000000000" />
<file name="Mockup splash.pptx" server="ftp.tailoredpages.com//weavapp/" local="130146844571461652" remote="130165356000000000" />
<file name="Nodes.png" server="ftp.tailoredpages.com//weavapp/" local="130101664600000000" remote="130165356000000000" />
<file name="placeholder.png" server="ftp.tailoredpages.com//weavapp/" local="130120797300000000" remote="130165356000000000" />
<file name="previewImage.png" server="ftp.tailoredpages.com//weavapp/" local="130122454920000000" remote="130165356000000000" />
<file name="rails.png" server="ftp.tailoredpages.com//weavapp/" local="130136604156839263" remote="130165356000000000" />
<file name="Results.png" server="ftp.tailoredpages.com//weavapp/" local="130146840055853374" remote="130165356000000000" />
<file name="weav-background-cocktail.jpg" server="ftp.tailoredpages.com//weavapp/" local="130146674743073278" remote="130165356000000000" />
<file name="weav-bcg.png" server="ftp.tailoredpages.com//weavapp/" local="130146832724484043" remote="130165356000000000" />
<file name="weav-gs.png" server="ftp.tailoredpages.com//weavapp/" local="130147008634890459" remote="130165356000000000" />
<file name="weav-ibm.png" server="ftp.tailoredpages.com//weavapp/" local="130146824609229877" remote="130165356000000000" />
<file name="weav-logo-tag-white.png" server="ftp.tailoredpages.com//weavapp/" local="130146823874217837" remote="130165356000000000" />
<file name="weav-mini.png" server="ftp.tailoredpages.com//weavapp/" local="130147846148579463" remote="130165356000000000" />
<file name="weav-pg.png" server="ftp.tailoredpages.com//weavapp/" local="130146832814019164" remote="130165356000000000" />
<file name="weav-td.png" server="ftp.tailoredpages.com//weavapp/" local="130147008187284858" remote="130165356600000000" />
</dwsync>